liquid_earth_sdk/__init__.py
liquid_earth_sdk/_version.py
liquid_earth_sdk/config.py
liquid_earth_sdk/api/__init__.py
liquid_earth_sdk/api/_utils_api.py
liquid_earth_sdk/api/le_api.py
liquid_earth_sdk/core/__init__.py
liquid_earth_sdk/core/output.py
liquid_earth_sdk/core/data/__init__.py
liquid_earth_sdk/core/data/le_data_types.py
liquid_earth_sdk/core/data/schemas.py
liquid_earth_sdk/modules/__init__.py
liquid_earth_sdk/modules/blob_client/__init__.py
liquid_earth_sdk/modules/blob_client/blob_interface.py
liquid_earth_sdk/modules/data_converter/__init__.py
liquid_earth_sdk/modules/data_converter/converter_interface.py
liquid_earth_sdk/modules/rest_client/__init__.py
liquid_earth_sdk/modules/rest_client/_links.py
liquid_earth_sdk/modules/rest_client/_utils.py
liquid_earth_sdk/modules/rest_client/rest_interface.py
liquid_earth_sdk-2025.1.0.dist-info/licenses/LICENSE.txt
tests/__init__.py
tests/conftest.py
tests/test_le_api_gempy_test.py
tests/test_le_api_test_cases.py
tests/test_token_api.py
tests/test_subsurface/__init__.py
tests/test_subsurface/test_subsurface_glt.py
tests/test_subsurface/test_subsurface_link.py
tests/test_subsurface/test_subsurface_obj.py
liquid_earth_sdk-2025.1.0.dist-info/METADATA
liquid_earth_sdk-2025.1.0.dist-info/WHEEL
liquid_earth_sdk-2025.1.0.dist-info/top_level.txt
liquid_earth_sdk-2025.1.0.dist-info/RECORD
