Metadata-Version: 2.4
Name: liquid_earth_sdk
Version: 2025.1.0
Summary: Python SDK to interact with Liquid Earth
Home-page: 
Author: Miguel de la Varga
Author-email: miguel@terranigma-solutions.com
License: EUPL-v1.2
License-File: LICENSE.txt
Requires-Dist: python-dotenv
Requires-Dist: pytest
Requires-Dist: python-dotenv
Requires-Dist: pydantic
Requires-Dist: azure-storage-blob
Requires-Dist: setuptools
Requires-Dist: requests
Requires-Dist: subsurface-terra
Dynamic: author
Dynamic: author-email
Dynamic: license
Dynamic: license-file
Dynamic: requires-dist
Dynamic: summary
